{
    "display": {
        "icon": {
            "id": "minecraft:filled_map"
        },
        "title": {
            "text": "⛶ Modifier"
        },
        "description": [
            {
                "text": "Spells that modify the next projectile",
                "color": "gray"
            }
        ],
        "frame": "challenge",
        "show_toast": false,
        "announce_to_chat": false,
        "hidden": false
    },
    "parent": "isc:spells/root",
    "criteria": {
        "isc:clone": {
            "trigger": "minecraft:tick",
            "conditions": {
                "player": [
                    {
                        "condition": "minecraft:entity_properties",
                        "entity": "this",
                        "predicate": {
                            "type_specific": {
                                "type": "minecraft:player",
                                "advancements": {
                                    "isc:spells/clone": true
                                }
                            }
                        }
                    }
                ]
            }
        },
        "isc:empower": {
            "trigger": "minecraft:tick",
            "conditions": {
                "player": [
                    {
                        "condition": "minecraft:entity_properties",
                        "entity": "this",
                        "predicate": {
                            "type_specific": {
                                "type": "minecraft:player",
                                "advancements": {
                                    "isc:spells/empower": true
                                }
                            }
                        }
                    }
                ]
            }
        },
        "isc:guide": {
            "trigger": "minecraft:tick",
            "conditions": {
                "player": [
                    {
                        "condition": "minecraft:entity_properties",
                        "entity": "this",
                        "predicate": {
                            "type_specific": {
                                "type": "minecraft:player",
                                "advancements": {
                                    "isc:spells/guide": true
                                }
                            }
                        }
                    }
                ]
            }
        },
        "isc:homing": {
            "trigger": "minecraft:tick",
            "conditions": {
                "player": [
                    {
                        "condition": "minecraft:entity_properties",
                        "entity": "this",
                        "predicate": {
                            "type_specific": {
                                "type": "minecraft:player",
                                "advancements": {
                                    "isc:spells/homing": true
                                }
                            }
                        }
                    }
                ]
            }
        },
        "isc:multishot": {
            "trigger": "minecraft:tick",
            "conditions": {
                "player": [
                    {
                        "condition": "minecraft:entity_properties",
                        "entity": "this",
                        "predicate": {
                            "type_specific": {
                                "type": "minecraft:player",
                                "advancements": {
                                    "isc:spells/multishot": true
                                }
                            }
                        }
                    }
                ]
            }
        },
        "isc:random_dir": {
            "trigger": "minecraft:tick",
            "conditions": {
                "player": [
                    {
                        "condition": "minecraft:entity_properties",
                        "entity": "this",
                        "predicate": {
                            "type_specific": {
                                "type": "minecraft:player",
                                "advancements": {
                                    "isc:spells/random_dir": true
                                }
                            }
                        }
                    }
                ]
            }
        },
        "isc:range_dec": {
            "trigger": "minecraft:tick",
            "conditions": {
                "player": [
                    {
                        "condition": "minecraft:entity_properties",
                        "entity": "this",
                        "predicate": {
                            "type_specific": {
                                "type": "minecraft:player",
                                "advancements": {
                                    "isc:spells/range_dec": true
                                }
                            }
                        }
                    }
                ]
            }
        },
        "isc:range_inc": {
            "trigger": "minecraft:tick",
            "conditions": {
                "player": [
                    {
                        "condition": "minecraft:entity_properties",
                        "entity": "this",
                        "predicate": {
                            "type_specific": {
                                "type": "minecraft:player",
                                "advancements": {
                                    "isc:spells/range_inc": true
                                }
                            }
                        }
                    }
                ]
            }
        },
        "isc:speed_dec": {
            "trigger": "minecraft:tick",
            "conditions": {
                "player": [
                    {
                        "condition": "minecraft:entity_properties",
                        "entity": "this",
                        "predicate": {
                            "type_specific": {
                                "type": "minecraft:player",
                                "advancements": {
                                    "isc:spells/speed_dec": true
                                }
                            }
                        }
                    }
                ]
            }
        },
        "isc:speed_inc": {
            "trigger": "minecraft:tick",
            "conditions": {
                "player": [
                    {
                        "condition": "minecraft:entity_properties",
                        "entity": "this",
                        "predicate": {
                            "type_specific": {
                                "type": "minecraft:player",
                                "advancements": {
                                    "isc:spells/speed_inc": true
                                }
                            }
                        }
                    }
                ]
            }
        },
        "isc:heavy_shot": {
            "trigger": "minecraft:tick",
            "conditions": {
                "player": [
                    {
                        "condition": "minecraft:entity_properties",
                        "entity": "this",
                        "predicate": {
                            "type_specific": {
                                "type": "minecraft:player",
                                "advancements": {
                                    "isc:spells/heavy_shot": true
                                }
                            }
                        }
                    }
                ]
            }
        },
        "isc:long_shot": {
            "trigger": "minecraft:tick",
            "conditions": {
                "player": [
                    {
                        "condition": "minecraft:entity_properties",
                        "entity": "this",
                        "predicate": {
                            "type_specific": {
                                "type": "minecraft:player",
                                "advancements": {
                                    "isc:spells/long_shot": true
                                }
                            }
                        }
                    }
                ]
            }
        },
        "isc:quick_shot": {
            "trigger": "minecraft:tick",
            "conditions": {
                "player": [
                    {
                        "condition": "minecraft:entity_properties",
                        "entity": "this",
                        "predicate": {
                            "type_specific": {
                                "type": "minecraft:player",
                                "advancements": {
                                    "isc:spells/quick_shot": true
                                }
                            }
                        }
                    }
                ]
            }
        },
        "isc:ghost": {
            "trigger": "minecraft:tick",
            "conditions": {
                "player": [
                    {
                        "condition": "minecraft:entity_properties",
                        "entity": "this",
                        "predicate": {
                            "type_specific": {
                                "type": "minecraft:player",
                                "advancements": {
                                    "isc:spells/ghost": true
                                }
                            }
                        }
                    }
                ]
            }
        },
        "isc:gravity": {
            "trigger": "minecraft:tick",
            "conditions": {
                "player": [
                    {
                        "condition": "minecraft:entity_properties",
                        "entity": "this",
                        "predicate": {
                            "type_specific": {
                                "type": "minecraft:player",
                                "advancements": {
                                    "isc:spells/gravity": true
                                }
                            }
                        }
                    }
                ]
            }
        },
        "isc:anti_gravity": {
            "trigger": "minecraft:tick",
            "conditions": {
                "player": [
                    {
                        "condition": "minecraft:entity_properties",
                        "entity": "this",
                        "predicate": {
                            "type_specific": {
                                "type": "minecraft:player",
                                "advancements": {
                                    "isc:spells/anti_gravity": true
                                }
                            }
                        }
                    }
                ]
            }
        },
        "isc:instant": {
            "trigger": "minecraft:tick",
            "conditions": {
                "player": [
                    {
                        "condition": "minecraft:entity_properties",
                        "entity": "this",
                        "predicate": {
                            "type_specific": {
                                "type": "minecraft:player",
                                "advancements": {
                                    "isc:spells/instant": true
                                }
                            }
                        }
                    }
                ]
            }
        },
        "isc:piercing": {
            "trigger": "minecraft:tick",
            "conditions": {
                "player": [
                    {
                        "condition": "minecraft:entity_properties",
                        "entity": "this",
                        "predicate": {
                            "type_specific": {
                                "type": "minecraft:player",
                                "advancements": {
                                    "isc:spells/piercing": true
                                }
                            }
                        }
                    }
                ]
            }
        },
        "isc:harmless": {
            "trigger": "minecraft:tick",
            "conditions": {
                "player": [
                    {
                        "condition": "minecraft:entity_properties",
                        "entity": "this",
                        "predicate": {
                            "type_specific": {
                                "type": "minecraft:player",
                                "advancements": {
                                    "isc:spells/harmless": true
                                }
                            }
                        }
                    }
                ]
            }
        },
        "isc:hidden": {
            "trigger": "minecraft:tick",
            "conditions": {
                "player": [
                    {
                        "condition": "minecraft:entity_properties",
                        "entity": "this",
                        "predicate": {
                            "type_specific": {
                                "type": "minecraft:player",
                                "advancements": {
                                    "isc:spells/hidden": true
                                }
                            }
                        }
                    }
                ]
            }
        },
        "isc:rainbow": {
            "trigger": "minecraft:tick",
            "conditions": {
                "player": [
                    {
                        "condition": "minecraft:entity_properties",
                        "entity": "this",
                        "predicate": {
                            "type_specific": {
                                "type": "minecraft:player",
                                "advancements": {
                                    "isc:spells/rainbow": true
                                }
                            }
                        }
                    }
                ]
            }
        },
        "isc:zigzag": {
            "trigger": "minecraft:tick",
            "conditions": {
                "player": [
                    {
                        "condition": "minecraft:entity_properties",
                        "entity": "this",
                        "predicate": {
                            "type_specific": {
                                "type": "minecraft:player",
                                "advancements": {
                                    "isc:spells/zigzag": true
                                }
                            }
                        }
                    }
                ]
            }
        },
        "isc:chaotic": {
            "trigger": "minecraft:tick",
            "conditions": {
                "player": [
                    {
                        "condition": "minecraft:entity_properties",
                        "entity": "this",
                        "predicate": {
                            "type_specific": {
                                "type": "minecraft:player",
                                "advancements": {
                                    "isc:spells/chaotic": true
                                }
                            }
                        }
                    }
                ]
            }
        },
        "isc:remote_cast": {
            "trigger": "minecraft:tick",
            "conditions": {
                "player": [
                    {
                        "condition": "minecraft:entity_properties",
                        "entity": "this",
                        "predicate": {
                            "type_specific": {
                                "type": "minecraft:player",
                                "advancements": {
                                    "isc:spells/remote_cast": true
                                }
                            }
                        }
                    }
                ]
            }
        },
        "isc:spiral": {
            "trigger": "minecraft:tick",
            "conditions": {
                "player": [
                    {
                        "condition": "minecraft:entity_properties",
                        "entity": "this",
                        "predicate": {
                            "type_specific": {
                                "type": "minecraft:player",
                                "advancements": {
                                    "isc:spells/spiral": true
                                }
                            }
                        }
                    }
                ]
            }
        },
        "isc:aim_assist": {
            "trigger": "minecraft:tick",
            "conditions": {
                "player": [
                    {
                        "condition": "minecraft:entity_properties",
                        "entity": "this",
                        "predicate": {
                            "type_specific": {
                                "type": "minecraft:player",
                                "advancements": {
                                    "isc:spells/aim_assist": true
                                }
                            }
                        }
                    }
                ]
            }
        },
        "isc:scaling": {
            "trigger": "minecraft:tick",
            "conditions": {
                "player": [
                    {
                        "condition": "minecraft:entity_properties",
                        "entity": "this",
                        "predicate": {
                            "type_specific": {
                                "type": "minecraft:player",
                                "advancements": {
                                    "isc:spells/scaling": true
                                }
                            }
                        }
                    }
                ]
            }
        },
        "isc:anchored": {
            "trigger": "minecraft:tick",
            "conditions": {
                "player": [
                    {
                        "condition": "minecraft:entity_properties",
                        "entity": "this",
                        "predicate": {
                            "type_specific": {
                                "type": "minecraft:player",
                                "advancements": {
                                    "isc:spells/anchored": true
                                }
                            }
                        }
                    }
                ]
            }
        },
        "isc:return": {
            "trigger": "minecraft:tick",
            "conditions": {
                "player": [
                    {
                        "condition": "minecraft:entity_properties",
                        "entity": "this",
                        "predicate": {
                            "type_specific": {
                                "type": "minecraft:player",
                                "advancements": {
                                    "isc:spells/return": true
                                }
                            }
                        }
                    }
                ]
            }
        },
        "isc:trick_shot": {
            "trigger": "minecraft:tick",
            "conditions": {
                "player": [
                    {
                        "condition": "minecraft:entity_properties",
                        "entity": "this",
                        "predicate": {
                            "type_specific": {
                                "type": "minecraft:player",
                                "advancements": {
                                    "isc:spells/trick_shot": true
                                }
                            }
                        }
                    }
                ]
            }
        },
        "isc:accelerate": {
            "trigger": "minecraft:tick",
            "conditions": {
                "player": [
                    {
                        "condition": "minecraft:entity_properties",
                        "entity": "this",
                        "predicate": {
                            "type_specific": {
                                "type": "minecraft:player",
                                "advancements": {
                                    "isc:spells/accelerate": true
                                }
                            }
                        }
                    }
                ]
            }
        },
        "isc:wave": {
            "trigger": "minecraft:tick",
            "conditions": {
                "player": [
                    {
                        "condition": "minecraft:entity_properties",
                        "entity": "this",
                        "predicate": {
                            "type_specific": {
                                "type": "minecraft:player",
                                "advancements": {
                                    "isc:spells/wave": true
                                }
                            }
                        }
                    }
                ]
            }
        },
        "isc:warp": {
            "trigger": "minecraft:tick",
            "conditions": {
                "player": [
                    {
                        "condition": "minecraft:entity_properties",
                        "entity": "this",
                        "predicate": {
                            "type_specific": {
                                "type": "minecraft:player",
                                "advancements": {
                                    "isc:spells/warp": true
                                }
                            }
                        }
                    }
                ]
            }
        },
        "isc:follow": {
            "trigger": "minecraft:tick",
            "conditions": {
                "player": [
                    {
                        "condition": "minecraft:entity_properties",
                        "entity": "this",
                        "predicate": {
                            "type_specific": {
                                "type": "minecraft:player",
                                "advancements": {
                                    "isc:spells/follow": true
                                }
                            }
                        }
                    }
                ]
            }
        },
        "isc:safe_shot": {
            "trigger": "minecraft:tick",
            "conditions": {
                "player": [
                    {
                        "condition": "minecraft:entity_properties",
                        "entity": "this",
                        "predicate": {
                            "type_specific": {
                                "type": "minecraft:player",
                                "advancements": {
                                    "isc:spells/safe_shot": true
                                }
                            }
                        }
                    }
                ]
            }
        },
        "isc:bouncy": {
            "trigger": "minecraft:tick",
            "conditions": {
                "player": [
                    {
                        "condition": "minecraft:entity_properties",
                        "entity": "this",
                        "predicate": {
                            "type_specific": {
                                "type": "minecraft:player",
                                "advancements": {
                                    "isc:spells/bouncy": true
                                }
                            }
                        }
                    }
                ]
            }
        }
    }
}