{
    "pools": [
        {
            "rolls": 1,
            "entries": [
                {
                    "type": "minecraft:loot_table",
                    "value": "isc:wands/basic"
                }
            ]
        }
    ],
    "functions": [
        {
            "function": "minecraft:set_custom_data",
            "tag": "{isc:{wand:{valid:1b, mana:130, cooldown:5, spells:[ 14, 14, 15, 9, 1 ]}}}"
        },
        {
            "function": "minecraft:reference",
            "name": "isc:wand/lore/unknown"
        }
    ]
}